tinyprog/__init__.py
tinyprog/__main__.py
tinyprog-1.0.23.dist-info/DESCRIPTION.rst
tinyprog-1.0.23.dist-info/METADATA
tinyprog-1.0.23.dist-info/RECORD
tinyprog-1.0.23.dist-info/WHEEL
tinyprog-1.0.23.dist-info/entry_points.txt
tinyprog-1.0.23.dist-info/metadata.json
tinyprog-1.0.23.dist-info/top_level.txt
