Metadata-Version: 2.0
Name: tinyprog
Version: 1.0.23
Summary: Programmer for FPGA boards using the TinyFPGA USB Bootloader (http://tinyfpga.com)
Home-page: https://github.com/tinyfpga/TinyFPGA-Bootloader/
Author: Luke Valenty
Author-email: luke@tinyfpga.com
License: UNKNOWN
Keywords: fpga,tinyfpga,programmer
Platform: UNKNOWN
Classifier: Development Status :: 5 - Production/Stable
Classifier: Environment :: Console
Classifier: Intended Audience :: Developers
Classifier: License :: OSI Approved :: GNU General Public License v2 (GPLv2)
Classifier: Programming Language :: Python :: 2
Classifier: Programming Language :: Python :: 3
Requires-Dist: intelhex (>=2.2.1,<3)
Requires-Dist: jsonmerge (>=1.4.0,<2)
Requires-Dist: packaging
Requires-Dist: pyserial (>=3,<4)
Requires-Dist: pyusb
Requires-Dist: six
Requires-Dist: tqdm (<5,>=4.19.5)
